Workbook
Name Categoria: 'Strutture ricettive'!$A$2:$A$1048576
Name Città: 'Strutture ricettive'!$D$2:$D$1048576
Name Denominazione: 'Strutture ricettive'!$B$2:$B$1048576
Name Indirizzo: 'Strutture ricettive'!$C$2:$C$1048576
Name Indirizzo_di_posta_elettronica: 'Strutture ricettive'!$G$2:$G$1048576
Name Indirizzo_internet: 'Strutture ricettive'!$F$2:$F$1048576
Name Localita: 'Strutture ricettive'!$E$2:$E$1048576
Name Nome_Struttura: '[1]Strutture ricettive'!$B$2:$B$1048576

Sheet Strutture ricettive
A1: Categoria | B1: Denominazione | C1: Indirizzo | D1: Città | E1: Localita | F1: Indirizzo internet | G1: Indirizzo di posta elettronica
A2: TURISMO RURALE | B2: COUNTRY HOUSE LOCALITA' GIROFALCO | C2: Via Girfalco, 26 | D2: URBINO | F2: www.girfalco.it | G2: info@girfalco.it
A3: ALTRI ALLOGGI PRIVATI | B3: STAGNOZZI STEFANIA | C3: Via Candigliano 5 | D3: ACQUALAGNA | E3: ACQUALAGNA | G3: gigliovitto@libero.it
A4: ALTRI ALLOGGI PRIVATI | B4: GORGOLINI ALESSANDRO | C4: Via San Gregorio 9 | D4: ACQUALAGNA | E4: ACQUALAGNA | G4: ale.gorgolini@gmail.com
A5: ALBERGHI | B5: LEON D'ORO | C5: Via Flaminia 213 | D5: ACQUALAGNA | E5: ACQUALAGNA
A6: ALBERGHI | B6: ALBERGO DOMUS MARIAE | C6: viale Ezio Scaglioni 17 | D6: ACQUALAGNA | E6: ACQUALAGNA | G6: giulianaspini@gmail.com
A7: ALTRI ALLOGGI PRIVATI | B7: TORRE COLOMBARA DI FRONTINO | C7: STRADA FRONTINO 24/B | D7: ACQUALAGNA | E7: ACQUALAGNA | G7: luccardi.sandro@gmail.com
A8: BED & BREAKFAST | B8: B&B AQUILEGIA | C8: via Furlo 12 | D8: ACQUALAGNA | E8: Furlo | F8: www.aquilegiabeb.com | G8: info@aquilegiabeb.com
A9: ALLOGGI AGRITURISTICI | B9: DEL FRONTINO | C9: strada frontino 23 | D9: ACQUALAGNA | E9: ACQUALAGNA
A10: ALBERGHI | B10: LA GINESTRA | C10: via Furlo 17 | D10: ACQUALAGNA | E10: ACQUALAGNA | F10: www.ginestrafurlo.it | G10: info@ginestrafurlo.it
A11: ALBERGHI | B11: BIRRA AL POZZO | C11: via Pianacce 12 | D11: ACQUALAGNA | E11: ACQUALAGNA | F11: www.birraalpozzo.it | G11: info@birraalpozzo.it
A12: BED & BREAKFAST | B12: B&B CRISTINI CRISTINA | C12: strada frontino 23 | D12: ACQUALAGNA | E12: ACQUALAGNA | G12: cri.cristini@alice.it
A13: BED & BREAKFAST | B13: B&B MARTELLONI CESARE | C13: via pianacce 67 | D13: ACQUALAGNA | E13: ACQUALAGNA | F13: www.lalocandadellabbazia.it | G13: info@lalocandadellabbazia.it
A14: ALBERGHI | B14: ALBERGO MEUBLE' SHINE | C14: via aldo gamba 54 | D14: ACQUALAGNA | E14: ACQUALAGNA
A15: ALLOGGI AGRITURISTICI | B15: AGRITURISMO CASTELLAGO | C15: strada Castellaro 18 | D15: ACQUALAGNA | E15: ACQUALAGNA | G15: castellago@virgilio.it
A16: ALBERGHI | B16: ALBERGO ANTICO FURLO | C16: via Flaminia 66 | D16: ACQUALAGNA | E16: ACQUALAGNA | F16: www.anticofurlo.it | G16: info@anticofurlo.it
A17: TURISMO RURALE | B17: CA' GARAVANO | C17: strada Frontino 21 | D17: ACQUALAGNA | E17: ACQUALAGNA | F17: www.cagaravano.com | G17: urbini.alessandro@alice.it
A18: ALTRI ALLOGGI PRIVATI | B18: IL CONIO DI DI GIOVANNI FEDERICO | C18: strada pietralatra 1 | D18: ACQUALAGNA | E18: ACQUALAGNA
A19: ALLOGGI AGRITURISTICI | B19: AGRITURISMO I CONTI | C19: via Pieve del Colle 11 b | D19: ACQUALAGNA | E19: pieve del colle | F19: www.agriturismoiconti.it | G19: info@agriturismoiconti.it
A20: ALLOGGI AGRITURISTICI | B20: LA COLOMBARA | C20: strada Frontino 24 | D20: ACQUALAGNA
A21: ALTRI ALLOGGI PRIVATI | B21: STROPPA GIUSEPPE | C21: strada San Gregorio 12 | D21: ACQUALAGNA | E21: Acqualagna | F21: http://lapanoramicadastroppa.webstarts.com/ | G21: stroppag@libero.it
A22: ALTRI ALLOGGI PRIVATI | B22: SERAFINI GIORGIA | D22: ACQUALAGNA
A23: ALTRI ALLOGGI PRIVATI | B23: BETTI VINCENZO | C23: via Pole 69 | D23: ACQUALAGNA
A24: ALLOGGI IN AFFITTO | B24: MARCHEHOLIDAY - CASALE DEGLI ULIVI | C24: strada San Gregorio 1 | D24: ACQUALAGNA | E24: loc.Ca Donnino | F24: www.marcheholiday.it/ulivi | G24: info@marcheholiday.it
A25: AREE DI SOSTA (PLEIN AIR) | B25: AREA SOSTA CAMPER PARCO LE QUERCE | C25: via Pianacce 1 | D25: ACQUALAGNA | E25: RISERVA NATURALE STATALE GOLA DEL FURLO | F25: parcodelfurlo.it | G25: info@parcodelfurlo.it
A26: ALTRI ALLOGGI PRIVATI | B26: BACCHIOCCHI MARIA ELISA | C26: via San Gregorio 17 | D26: ACQUALAGNA | G26: remigio.battistelli@gmail.com
A27: ALTRI ALLOGGI PRIVATI | B27: MARCHETTI LORENZA | C27: via Fossato 37/b | D27: ACQUALAGNA | G27: thomas.clementi@hotmail.it
A28: BED & BREAKFAST | B28: B&B BISCUBIO | C28: via Circonvallazione 46 | D28: APECCHIO | G28: marcellamartinelli17@gmail.com
A29: ALBERGHI | B29: GHIGHETTA | C29: via Borgo Mazzini 40 | D29: APECCHIO | G29: doradimaggio@libero.it
A30: ALLOGGI AGRITURISTICI | B30: AGRITURISMO LA ROCCA | D30: APECCHIO | E30: località la rocca | G30: a.parlani@alice.it
A31: ALLOGGI AGRITURISTICI | B31: AGRITURISMO CA' PIERPAOLI | D31: APECCHIO | E31: località Ca' Pierpaoli | F31: www.chipierpaoli.it | G31: info@chipierpaoli.it
A32: ALLOGGI AGRITURISTICI | B32: AGRITURISMO PIANDIMOLINO | C32: località Pian di Molino 16 | D32: APECCHIO | E32: PIAN DI MOLINO | F32: www.agriturismopiandimolino.it | G32: info@agriturismopiandimolino.it
A33: BED & BREAKFAST | B33: B&B GRANCI MARIA GRAZIA | C33: via Martiri della Liberta' 20 | D33: APECCHIO | E33: APECCHIO
A34: TURISMO RURALE | B34: LE CIOCCHE | D34: APECCHIO | E34: APECCHIO | G34: ale_cipi@live.it
A35: ALLOGGI AGRITURISTICI | B35: FONTE SOMMA | D35: APECCHIO | E35: loc.Fontesomma | F35: www.fontesomma.it | G35: info@fontesomma.it
A36: TURISMO RURALE | B36: COL ALPI | C36: via Circonvallazione 40 | D36: APECCHIO | E36: APECCHIO | G36: ilaesimo@virgilio.it
A37: TURISMO RURALE | B37: COUNTRY HOUSE CACCIABOCCA | C37: vocabolo Caselle 100 | D37: APECCHIO | E37: APECCHIO | F37: www.countryhousechiciabocca.it | G37: info@countryhousechiciabocca.it
A38: BED & BREAKFAST | B38: B&B MOCHI EDMONDO ADOLFO FEDERICO | C38: via dante alighieri 41 | D38: APECCHIO | E38: APECCHIO | G38: elenamochi@hotmail.it
A39: AREE DI SOSTA (PLEIN AIR) | B39: AREA DI SOSTA CAMPER | D39: APECCHIO | E39: APECCHIO
A40: ALLOGGI IN AFFITTO | B40: AFFITTACAMERE APPENNINO | C40: via Garibaldi 9 | D40: APECCHIO | G40: marcellamartinelli17@gmail.com
A41: ALLOGGI AGRITURISTICI | B41: AGRITURISMO PIEVE DI SAN PAOLO | C41: San Paolo di Fagnille 29 | D41: APECCHIO | E41: San Paolo di Fagnille | F41: www.pievesp.it | G41: info@pievesp.it
A42: ALLOGGI IN AFFITTO | B42: CASA DELLE ROSE | D42: APECCHIO | E42: APECCHIO | F42: www.valguerriera.it | G42: info@valguerriera.it
A43: ALLOGGI IN AFFITTO | B43: VECCHIA FORNACE | C43: vocabolo chignucci 1 | D43: APECCHIO | E43: APECCHIO | F43: www.valguerriera.it | G43: info@valguerriera.it
A44: ALLOGGI IN AFFITTO | B44: ESSICCATOIO | C44: vocabolo val d' acqua 1 | D44: APECCHIO | E44: APECCHIO | F44: www.valguerriera.it | G44: info@valguerriera.it
A45: TURISMO RURALE | B45: COUNTRY HOUSE LA SPINA | C45: vocabolo spina 1 | D45: APECCHIO | E45: APECCHIO | F45: www.countryhouselaspina.it | G45: info@countryhouselaspina.it
A46: ALLOGGI AGRITURISTICI | B46: CA' QUATTROCCHI | C46: via Roma 1 | D46: APECCHIO | E46: APECCHIO
A47: TURISMO RURALE | B47: LUCARAIA | C47: localita' Lucaraia 1 | D47: APECCHIO | E47: APECCHIO | G47: lpraziendaagricola@gmail.com
A48: ALBERGHI | B48: MONTENERONE | C48: localita' Pian di Trebbio 81 | D48: APECCHIO | E48: APECCHIO | F48: www.hotelmontenerone.it | G48: info@hotelmontenerone.it
A49: TURISMO RURALE | B49: COL DI FIORE | C49: loc Col di Fiore snc | D49: APECCHIO | E49: APECCHIO | G49: lpraziendaagricola@gmail.com
A50: ALLOGGI AGRITURISTICI | B50: CASELLINA | C50: loc. la Casellina 1 | D50: APECCHIO | E50: APECCHIO | G50: lpraziendaagricola@gmail.com
A51: ALLOGGI AGRITURISTICI | B51: TAVERNA | C51: vocabolo caselle 1 | D51: APECCHIO | E51: APECCHIO | G51: marialaura@jumpi.it;
A52: ALLOGGI AGRITURISTICI | B52: CHIGNONI | C52: vocabolo Chignoni 1 | D52: APECCHIO | E52: APECCHIO | F52: www.chignoni.it | G52: info@chignoni.it
A53: ALLOGGI AGRITURISTICI | B53: CA' CIRIGIOLO | C53: Loc. Casa Nuova di Cirigiolo s/n | D53: APECCHIO | E53: Apecchio | F53: www.cacirigiolo.it | G53: info@cacirigiolo.it
A54: ALLOGGI AGRITURISTICI | B54: VAL DEL LAGO | C54: vocabolo Acquapartita 1 | D54: APECCHIO | E54: loc. Val del Lago | G54: lpraziendaagricola@gmail.com
A55: ALLOGGI AGRITURISTICI | B55: CASELLE | D55: APECCHIO | E55: Apecchio | G55: marialaura@jumpi.it
A56: OSTELLI PER LA GIOVENTU' | B56: OSTELLO DELLA GIOVENTU' LA CHIUSURA (CUCCHIARINI ALDO LORIS) | C56: via dante alighieri 1 | D56: APECCHIO | E56: APECCHIO | G56: cooplamacina@info-net.it
A57: CASE PER FERIE | B57: VILLA SANTA MARIA | C57: via Cagli 89 | D57: APECCHIO | E57: fraz. Serravalle
A58: BED & BREAKFAST | B58: B&B IL BORGO | C58: BORGO MAZZINI 28 | D58: APECCHIO | E58: APECCHIO | G58: stevemugs@gmail.com
A59: ALLOGGI IN AFFITTO | B59: IL POGGIO DI D'ANGELI LIDIA AFFITTACAMERE | C59: Via Poggio San Giovanni 17 | D59: AUDITORE | E59: AUDITORE | G59: info@baita7nani.com
A60: ALLOGGI IN AFFITTO | B60: IL POGGIO DI D'ANGELI LIDIA | C60: Via Poggio San Giovanni 9 | D60: AUDITORE | E60: AUDITORE | G60: info@baita7nani.com
A61: BED & BREAKFAST | B61: B&B IL GIARDINO DELLE NOCI | C61: Località Molino Ca' Guerra 48 | D61: AUDITORE | E61: loc. Casinina | G61: ilariasanti89@libero.it
A62: ALBERGHI | B62: IL TORRIONE | C62: via circonvallazione 14 | D62: AUDITORE | E62: AUDITORE | F62: www.albergoiltorrione.it | G62: info@albergoiltorrione.it
A63: ALBERGHI | B63: ANTICA OSTERIA DA ORESTE | C63: via Risorgimento 4 | D63: AUDITORE | E63: frazione CASININA | F63: www.osteria-daoreste.it | G63: info@osteria-daoreste.it
A64: TURISMO RURALE | B64: COUNTRY HOUSE VILLA CISCA | C64: localita' molino fulvi 14 | D64: AUDITORE | E64: AUDITORE | F64: www.villacisca.com | G64: info@villacisca.com
A65: BED & BREAKFAST | B65: B&B TELE GIANNA | C65: via G. Leopardi 6 | D65: AUDITORE | E65: CASININA | F65: www.bb.telegianna.it | G65: carla2009@alice.it
A66: ALTRI ALLOGGI PRIVATI | B66: LA LUNA NELL'ORTO | C66: via Madonna Rafaneto 18 | D66: BARCHI | E66: loc.Rafaneto | F66: www.lalunanellorto.it | G66: petrabartels@libero.it
A67: ALLOGGI IN AFFITTO | B67: LA GIRAVOLTA | C67: via G. Campioli 10 | D67: BARCHI | F67: www.lagiravolta.eu | G67: info@lagiravolta.eu
A68: ALLOGGI IN AFFITTO | B68: VILLA RODI | C68: via Montesoffio 45 | D68: BARCHI | G68: d.falcinelli@cia.it
A69: ALTRI ALLOGGI PRIVATI | B69: VILLA AGAPANTUS | C69: via Villa di Monte Campagna 27 | D69: BARCHI | G69: francini_m@hotmail.com
A70: ALLOGGI AGRITURISTICI | B70: FONTE PAROLLA AGRITURISMO | C70: via Villa del Monte Campagna 13 | D70: BARCHI | E70: loc. Villa del Monte | F70: www.fonteparolla.it | G70: info@fonteparolla.it
A71: ALLOGGI AGRITURISTICI | B71: FORESTERIA AGRITURISTICA STRADA DEI CAMPIOLI | C71: via Giardino Campioli 31 | D71: BARCHI | F71: www.stradadeicampioli.it | G71: info@stradadeicampioli.it
A72: TURISMO RURALE | B72: COUNTRY HOUSE MONTESOFFIO | C72: localita' montesoffio 5 | D72: BARCHI | E72: BARCHI | F72: www.montesoffio.com | G72: info@montesoffio.com
A73: AREE DI SOSTA (PLEIN AIR) | B73: AREA DI SOSTA CAMPER | D73: BARCHI
A74: ALLOGGI AGRITURISTICI | B74: CAL FATTORE | C74: via Case Sparse snc | D74: BELFORTE ALL'ISAURO | G74: elebarbie@hotmail.it
A75: ALTRI ALLOGGI PRIVATI | B75: ROSSI ROSSANO | C75: via Angelini 4 | D75: BELFORTE ALL'ISAURO | G75: rossanorossi@hotmail.com
A76: ALTRI ALLOGGI PRIVATI | B76: CASALE FATTORIA GOSTOLI | C76: via Molino 16 | D76: BELFORTE ALL'ISAURO | G76: ilenia.battiato@tiscali.it
A77: ALBERGHI | B77: HOTEL LA RUPE | C77: via Meta 76 | D77: BORGO PACE | E77: BORGO PACE | G77: elisa@emtur.it
A78: BED & BREAKFAST | B78: B&B QUIETE SUL META | C78: via Papa Clemente XI 4 | D78: BORGO PACE | F78: www.quietesulmeta.com | G78: info@quietesulmeta.com
A79: BED & BREAKFAST | B79: B&B VALDERICARTE | C79: loc. Valderica 8 | D79: BORGO PACE | E79: LAMOLI | F79: www.valdericarte.com | G79: stella@valdericarte.com
A80: ALLOGGI AGRITURISTICI | B80: AGRITURISMO MORETTI MARCO | C80: localita' Campovecchio 1 | D80: BORGO PACE | E80: BORGO PACE
A81: ALBERGHI | B81: ALBERGO OASI SAN BENEDETTO | C81: via dell'Abbazia 7 | D81: BORGO PACE | E81: LAMOLI | G81: coloriappennino@libero.it
A82: ALLOGGI IN AFFITTO | B82: RANCO FABBRO | D82: BORGO PACE | E82: PARCHIULE | G82: prenotazioni@lamacina.it
A83: AREE DI SOSTA (PLEIN AIR) | B83: AREA DI SOSTA CAMPER | D83: BORGO PACE | E83: LOC. LAMOLI
A84: ALLOGGI AGRITURISTICI | B84: AGRITURISMO SANTI GILBERTO | C84: via Lame 18 | D84: BORGO PACE | E84: loc. Parchiule
A85: BED & BREAKFAST | B85: B&B AURO di BERNARDINI IVO | C85: loc. Molino 19 | D85: BORGO PACE | E85: BORGO PACE | G85: ivobernardini@libero.it
A86: ALLOGGI AGRITURISTICI | B86: AGRITURISMO ALPE DELLA LUNA | D86: BORGO PACE | E86: Vildonnino | F86: http://www.alpedellaluna.it/ | G86: agr@alpedellaluna.it
A87: ALBERGHI | B87: LA DILIGENZA | C87: piazza del Pino 9 | D87: BORGO PACE | E87: BORGO PACE | F87: www.anticalocandaladiligenza.it | G87: info@centrobebladiligenza.it
A88: RIFUGI | B88: OASI SAN BENEDETTO | C88: via dell' Abbazia 13 | D88: BORGO PACE | E88: BORGO PACE | G88: trabaria@libero.it
A89: OSTELLI PER LA GIOVENTU' | B89: OSTELLO PER LA GIOVENTU' | C89: via dell' Abbazia 40 | D89: BORGO PACE | E89: LAMOLI | G89: lamoli@oasisanbenedetto.it
A90: ALLOGGI AGRITURISTICI | B90: AGRITURISMO IL GINEPRO | C90: localita' Figgiano 46 | D90: BORGO PACE | E90: BORGO PACE | G90: info@ilgineprofigiano.com
A91: ALLOGGI AGRITURISTICI | B91: AGRITURISMO SACCHIA ART FARM | D91: BORGO PACE | E91: loc. Sacchia | F91: www.sacchiafarm.com | G91: info@sacchiafarm.com
A92: ALTRI ALLOGGI PRIVATI | B92: PAOLO CANGINI | C92: loc. Acquaviva 25 | D92: CAGLI
A93: ALTRI ALLOGGI PRIVATI | B93: PAVONI LUCIO | C93: via Don Minzoni, 66 66/a | D93: CAGLI | G93: lucia.pavoni.18@gmail.com
A94: ALTRI ALLOGGI PRIVATI | B94: GIUNTI FRANCESCO | C94: via Case Sparse 85 | D94: CAGLI | E94: loc. Naro
A95: BED & BREAKFAST | B95: B&B VILLA ADA | C95: via B.Buozzi 37 | D95: CAGLI | F95: http://villaadacagli.tumblr.com/ | G95: villaadacagli@gmail.com
A96: TURISMO RURALE | B96: COUNTRY HOUSE IL GIORDANO,SASSO DELLA ROCCA | C96: via Centro Pieia 16,45 | D96: CAGLI | E96: Centro Pieia 16; Centro Pieia 45 | F96: www.pieiavacanze.it | G96: info@pieiavacanze.it
A97: BED & BREAKFAST | B97: B&B LA VILLA DEGLI ORTI | C97: via Flaminia Nord 153 | D97: CAGLI | G97: m.tassi@libero.it
A98: ALLOGGI AGRITURISTICI | B98: L'ONCIA | D98: CAGLI | E98: loc. Ca' Serra | G98: zio.mele@libero.it
A99: TURISMO RURALE | B99: VILLA DEGLI ORTI | C99: via Flaminia Nord 153 | D99: CAGLI | G99: info@ortiamo.it
A100: ALLOGGI IN AFFITTO | B100: LA PIAZZA | C100: p.zza Matteotti 6 | D100: CAGLI | F100: www.casavacanzelapiazza.it | G100: info@casavacanzelapiazza.it
...

Sheet RICERCA
B1: RICERCA STRUTTURA
B3: NOME STRUTTURA | C3: COUNTRY HOUSE LOCALITA' GIROFALCO | E3: Categoria | H3: Città | J3: Categoria | K3: Denominazione | L3: Indirizzo | M3: Città | N3: Localita | O3: Indirizzo internet | P3: Indirizzo di posta elettronica
B4: CITTA' | C4: =_xlfn.XLOOKUP($C$3,'Strutture ricettive'!B:B,'Strutture ricettive'!D:D,"Non trovata") -> URBINO | E4: BED & BREAKFAST | F4: =COUNTIF('Strutture ricettive'!A:A,E4) -> 1809 | H4: URBINO | J4: TURISMO RURALE | K4: COUNTRY HOUSE LOCALITA' GIROFALCO | L4: Via Girfalco, 26 | M4: URBINO | O4: www.girfalco.it | P4: info@girfalco.it
B5: INDIRIZZO | C5: =_xlfn.XLOOKUP($C$3,'Strutture ricettive'!B:B,'Strutture ricettive'!C:C,"Non trovata") -> Via Girfalco, 26 | E5: STABILIMENTI BALNEARI | F5: =COUNTIF('Strutture ricettive'!A:A,E5) -> 850 | J5: ALTRI ALLOGGI PRIVATI | K5: PESCHKE MARTIN MICHAEL ERNST | L5: strada provinciale Peglio San Donato 17 | M5: URBINO | O5: www.capiero.it | P5: email.capiero@googlemail.com
B6: EMAIL | C6: =_xlfn.XLOOKUP($C$3,'Strutture ricettive'!B:B,'Strutture ricettive'!G:G,"Non trovata") -> info@girfalco.it | E6: ALLOGGI AGRITURISTICI | F6: =COUNTIF('Strutture ricettive'!A:A,E6) -> 830 | J6: BED & BREAKFAST | K6: B&B IL MONCHETTO | L6: via Monte Pallotta 31 | M6: URBINO | N6: Cà Staccolo | P6: lauraquaresima@virgilio.it
B7: INDIRIZZO WEB | C7: =_xlfn.XLOOKUP($C$3,'Strutture ricettive'!B:B,'Strutture ricettive'!F:F,"Non trovata") -> www.girfalco.it | E7: ALBERGHI | F7: =COUNTIF('Strutture ricettive'!A:A,E7) -> 814 | J7: ALTRI ALLOGGI PRIVATI | K7: VILLA LAURA | L7: via E. Mattei 30 | M7: URBINO | O7: www.vacanzeavillalaura.it | P7: vacanzevillalaura@gmail.com
B8: Numero totale strutture | C8: =COUNTA('Strutture ricettive'!B:B)-1 -> 6258 | E8: ALTRI ALLOGGI PRIVATI | F8: =COUNTIF('Strutture ricettive'!A:A,E8) -> 721 | J8: BED & BREAKFAST | K8: B&B IL CASALE DEL DUCA | L8: strada provinciale Montefabbri 104 | M8: URBINO | N8: Cal Duca | O8: www.ilcasaledelduca.it | P8: info@ilcasaledelduca.it
B9: Numero strutture per LOCALITA' | C9: =COUNTIF('Strutture ricettive'!D:D,C4) -> 144 | E9: ALLOGGI IN AFFITTO | F9: =COUNTIF('Strutture ricettive'!A:A,E9) -> 541 | J9: BED & BREAKFAST | K9: DOMENICA B&B | L9: via Don Luigi Sturzo 11 | M9: URBINO | N9: loc. Canavaccio | P9: patrizia.diotallevi62@hotmail.com
E10: TURISMO RURALE | F10: =COUNTIF('Strutture ricettive'!A:A,E10) -> 304 | J10: BED & BREAKFAST | K10: B&B CA' FABBRO | L10: strada provinciale Pieve di Cagna 33/35 | M10: URBINO | P10: mprossi1@virgilio.it
B11: Esercizio 10 | E11: CAMPEGGI | F11: =COUNTIF('Strutture ricettive'!A:A,E11) -> 93 | J11: BED & BREAKFAST | K11: B&B SASSO FIORITO | L11: via Monte Pallotta 12 | M11: URBINO | N11: loc. Sasso | P11: mauro.sisti@alice.it
B12: Probabilita dai conteggi | E12: AREE DI SOSTA (PLEIN AIR) | F12: =COUNTIF('Strutture ricettive'!A:A,E12) -> 86 | J12: ALLOGGI AGRITURISTICI | K12: CA' LUPINO | L12: via Cà Bergamo 44 | M12: URBINO | O12: www.calupino.it | P12: info@calupino.it
B13: P(Albergo) | C13: =F7/C8 -> 0.13007351 | E13: CASE PER FERIE | F13: =COUNTIF('Strutture ricettive'!A:A,E13) -> 82 | J13: BED & BREAKFAST | K13: B&B A CASA MIA | L13: via Colonna 25 | M13: URBINO | N13: loc. Trasanni | P13: tecla1111@yahoo.it
B14: P(Bed & Breakfast) | C14: =F4/C8 -> 0.28906999 | E14: RESIDENZE TURISTICO ALBERGHIERE | F14: =COUNTIF('Strutture ricettive'!A:A,E14) -> 52 | J14: BED & BREAKFAST | K14: B&B AMPIAVISTA | L14: via Bramante 66/a | M14: URBINO | P14: ampiavista@libero.it
B15: P(2 Alberghi su 2 Estrazioni) | C15: =(F7/C8)^2 -> 0.016919117 | E15: OSTELLI PER LA GIOVENTU' | F15: =COUNTIF('Strutture ricettive'!A:A,E15) -> 30 | J15: BED & BREAKFAST | K15: B&B CASA NELLA | L15: via dei Vasari 13 | M15: URBINO | P15: susix1it@yahoo.it
E16: VILLAGGI TURISTICI | F16: =COUNTIF('Strutture ricettive'!A:A,E16) -> 17 | J16: ALTRI ALLOGGI PRIVATI | K16: CA' AURORA | L16: via Nazionale Boccatrabaria ovest 144 | M16: URBINO
E17: RIFUGI | F17: =COUNTIF('Strutture ricettive'!A:A,E17) -> 16 | J17: ALBERGHI | K17: HOTEL MAMIANI | L17: via Errigo Bernini 6 | M17: URBINO | N17: URBINO | O17: www.hotelmamiani.it | P17: info@hotelmamiani.it
E18: ALTRI ESERCIZI RICETTIVI | F18: =COUNTIF('Strutture ricettive'!A:A,E18) -> 13 | J18: BED & BREAKFAST | K18: B&B CA' IMELDE | L18: via Bocca Trabaria 123 | M18: URBINO | P18: arcalavalle@gmail.com
J19: BED & BREAKFAST | K19: B&B VILLA CINI | L19: via S.P.Montefabbri 17 | M19: URBINO | O19: www.bbvillacini.com | P19: info@bbvillacini.com
J20: ALTRI ALLOGGI PRIVATI | K20: ACERO FRANCESCO E FILIPPO | L20: via Monte Polo 10 | M20: URBINO | P20: m.g.acero@alice.it
J21: ALTRI ALLOGGI PRIVATI | K21: ACERO MARIA GRAZIA | L21: via Monte Polo 8 | M21: URBINO | P21: m.g.acero@alice.it
J22: BED & BREAKFAST | K22: B&B LA NATURA | L22: via San Bartolo - loc. Rancitella 2 | M22: URBINO | N22: loc. Rancitella - via San Bartolo | O22: www.bblanatura.it | P22: info@bblanatura.it
J23: BED & BREAKFAST | K23: B&B LA CASETTA DEL BORGO | L23: via del Borgo Antico 5 | M23: URBINO | N23: loc.Pantiere | P23: beblacasettadelborgo@gmail.com
J24: BED & BREAKFAST | K24: B&B MARIA GIUSEPPINA MASTORE | L24: via San Marino 19 | M24: URBINO | P24: pinamastore@gmail.com
J25: BED & BREAKFAST | K25: B&B ALBORNOZ | L25: via dei Maceri 23 | M25: URBINO | O25: www.bbalbornoz.com | P25: email@bbalbornoz.com
J26: ALLOGGI AGRITURISTICI | K26: CA' FERRO | L26: Bocca Trabaria Ovest 126 | M26: URBINO | N26: Tufo | O26: agriturismocaferro.it | P26: fogliaa84@libero.it
J27: BED & BREAKFAST | K27: B&B SANPOLO 1544 | L27: via Aurelio Saffi 3 | M27: URBINO | O27: www.sanpolo1544.it | P27: info@sanpolo1544.it
J28: BED & BREAKFAST | K28: B&B IL GHETTO | L28: via Stretta 31 | M28: URBINO | N28: URBINO | O28: www.ilghetto.net | P28: ilghettourbino@gmail.com
J29: ALTRI ESERCIZI RICETTIVI | K29: ISTITUTO SANTA FELICITA | L29: via del fiancale 1 | M29: URBINO | N29: URBINO
J30: ALTRI ESERCIZI RICETTIVI | K30: PENSIONATO MARIA IMMACOLATA | L30: via giuseppe mazzini 36 | M30: URBINO | N30: URBINO | P30: mpvurbino@tiscali.it
J31: BED & BREAKFAST | K31: ANNA BED & BREAKFAST | L31: via nazionale 1 | M31: URBINO | N31: URBINO | O31: www.anna-bed-breakfast.it | P31: ardu09@gmail.com
J32: BED & BREAKFAST | K32: B&B VILLA GERHARDT | L32: localita' rancitella via san bartolo 23 | M32: URBINO | N32: URBINO
J33: TURISMO RURALE | K33: COUNTRY HOUSE AI CIPRESSI | L33: via mainardi 3 | M33: URBINO | N33: URBINO | O33: http://www.cipressiurbino.it | P33: cipressiurbino@gmail.com
J34: BED & BREAKFAST | K34: B&B DELLE DUCHESSE | L34: via Santa Margherita 22 | M34: URBINO | N34: URBINO | O34: www.albergoraffaello.com | P34: info@albergoraffaello.com
J35: BED & BREAKFAST | K35: B&B LA VALLE | L35: Via della valle 1 | M35: URBINO | N35: URBINO | O35: www.bblavalle.com | P35: prenotazioni@bblavalle.com
J36: BED & BREAKFAST | K36: B&B ACACIA | L36: via strada provinciale numero 9 feltresca 63 | M36: URBINO | N36: URBINO | O36: www.acaciaurbino.it | P36: sdenti@libero.it
J37: BED & BREAKFAST | K37: B&B ABACO - ALMA DOMUS | L37: via mainardi 1 | M37: URBINO | N37: URBINO | O37: www.almadomus.it | P37: almadomus@gmail.com
J38: ALLOGGI AGRITURISTICI | K38: IL CASALE NEL TUFO | L38: localita' Rancitella 1 | M38: URBINO | N38: URBINO | P38: faustofoglietta@interfree.it
J39: ALLOGGI AGRITURISTICI | K39: AGRITURISMO CA' MATTIOLI | L39: via Checiccarino 17 | M39: URBINO | N39: loc. Montecalende | P39: m.romagnoli@cia.it
J40: BED & BREAKFAST | K40: B&B URBINO | L40: via Fornace 1 | M40: URBINO | N40: URBINO | P40: marosx@vodafone.it
J41: BED & BREAKFAST | K41: B&B SAN FRANCESCO | L41: via raffaello 9 | M41: URBINO | N41: URBINO | O41: www.bbsanfrancescourbino.com | P41: info@bbsanfrancescourbino.com
J42: BED & BREAKFAST | K42: B&B VILLA LIBERTY | L42: viale antonio gramsci 22 | M42: URBINO | N42: URBINO | P42: info@bbaquilone.com
J43: BED & BREAKFAST | K43: B&B At VILLA SAN MARTINO | L43: via ca' le suore 12 | M43: URBINO | N43: URBINO | O43: www.villasanmartino.net | P43: villasanctusmartini@libero.it
J44: BED & BREAKFAST | K44: B&B AL NIDO | L44: Via strada provinciale montefabbri 32 | M44: URBINO | N44: URBINO | P44: rettori@libero.it
J45: BED & BREAKFAST | K45: B&B LE CALLE | L45: via Paolo Uccello 4 | M45: URBINO | N45: LOCALITA' TRASANNI | O45: http://bblecalle.it | P45: le.calle@yahoo.it
J46: BED & BREAKFAST | K46: B&B AI CIPRESSI | L46: via Mainardi 3 | M46: URBINO | N46: URBINO | O46: www.cipressiurbino.it | P46: cipressiurbino@gmail.com
J47: BED & BREAKFAST | K47: B&B SANTA MARGHERITA | L47: via Santa Margherita 3 | M47: URBINO | N47: URBINO
J48: BED & BREAKFAST | K48: B&B LA SCUOLA | L48: via palazzo del piano 3 | M48: URBINO | N48: URBINO | O48: www.bblascuola.it/ | P48: acecco@tin.it
J49: ALLOGGI AGRITURISTICI | K49: AGRITURISMO CA' VANZO | L49: via San Giacomo in Foglia 8 | M49: URBINO | N49: URBINO | P49: info@urbinoresort.it
J50: BED & BREAKFAST | K50: B&B VILLA BANCI di CIOPPI STEFANO | L50: via Rancitella 23 | M50: URBINO | O50: www.villabanci.it | P50: villabanci@libero.it
J51: BED & BREAKFAST | K51: AL NOCE BIANCO | L51: CA' DONDO 44 | M51: URBINO | N51: SAN DONATO | O51: www.alnocebianco.it | P51: cesane@libero.it
J52: BED & BREAKFAST | K52: B&B CASTELBOCCIONE | L52: castelboccione 3 | M52: URBINO | N52: TRASANNI | O52: B&B Castelboccione | P52: bbcastelboccione@gmail.com
J53: BED & BREAKFAST | K53: B&B VILLA VITTORIA | L53: S. P. DELLE CESANE 43 | M53: URBINO | P53: cirella23@libero.it
J54: CASE PER FERIE | K54: DOMUS URBINO PALAZZO ANGELONI | M54: URBINO
J55: CASE PER FERIE | K55: DOMUS URBINO PIEVE SAN CASSIANO | M55: URBINO | P55: prenotazioni@domus-urbino.it
J56: BED & BREAKFAST | K56: B&B CA' BARTOCCIO | L56: S.P. Montefabbri 109 | M56: URBINO | P56: cabartoccio@tiscali.it
J57: ALLOGGI AGRITURISTICI | K57: CA' MIGNONE | L57: strada provinciale le Cesane 43 | M57: URBINO | P57: agricamignone@libero.it
J58: BED & BREAKFAST | K58: B&B GLI AURI | L58: via San Bernardino 51 | M58: URBINO | N58: URBINO | P58: beb.gliauri@gmail.com
J59: BED & BREAKFAST | K59: B&B LA BELLA URBINO | L59: circonvallazione giro dei debitori 12 | M59: URBINO | N59: URBINO | P59: francescogtt@hotmail.it
J60: ALLOGGI IN AFFITTO | K60: IL CORTEGIANO | L60: via federico veterani 1 | M60: URBINO | N60: URBINO | P60: ilcortegiano@libero.it
J61: ALLOGGI AGRITURISTICI | K61: LA FORNACE | L61: via Bocca Trabaria Ovest 66/74 | M61: URBINO | N61: URBINO | P61: cavalentino58@gmail.com - cavalentino@pec.it
J62: BED & BREAKFAST | K62: B&B CAL TORELLO | L62: via strada provinciale montefabbri 87 | M62: URBINO | N62: PALLINO | O62: http://www.caltorello.it | P62: caltorello@gmail.com
J63: BED & BREAKFAST | K63: B&B L'ANGOLO FIORITO | L63: via strada provinciale pieve di cagna 21 | M63: URBINO | N63: RANCITELLA | P63: bblangolofiorito@libero.it
J64: BED & BREAKFAST | K64: B&B VILLA ANJANA | L64: via S. Eufemia 7/9 | M64: URBINO | N64: S.EUFEMIA | O64: www.villaanjana.altervista.org | P64: villaanjana@libero.it
J65: ALLOGGI IN AFFITTO | K65: POGGIO DEI PRUGNOLI di MARINA ARCANGELI | L65: loc.la Marcella Strada provinciale Tavoleto 31 | M65: URBINO | N65: URBINO | O65: www.poggiodeiprugnoli.it | P65: info@poggiodeiprugnoli.it
J66: ALBERGHI | K66: BONCONTE | L66: via delle mura 28 | M66: URBINO | N66: URBINO | O66: www.viphotels.it | P66: bonconte@viphotels.it
J67: ALBERGHI | K67: DEI DUCHI | L67: via giannetto dini 12 | M67: URBINO | N67: URBINO | O67: www.viphotels.it | P67: deiduchi@viphotels.it
J68: ALBERGHI | K68: ITALIA | L68: corso giuseppe garibaldi 32 | M68: URBINO | N68: URBINO | O68: www.albergo-italia-urbino.it | P68: info@albergo-italia-urbino.it
J69: ALBERGHI | K69: LA MERIDIANA | L69: via urbinate 43 | M69: URBINO | N69: URBINO | O69: www.la-meridiana.com | P69: meridiana@la-meridiana.com
J70: ALBERGHI | K70: NENE' | L70: via biancalana- STRADA ROSSA 39 | M70: URBINO | N70: URBINO | O70: www.neneurbino.com | P70: nene@neneurbino.com
J71: ALBERGHI | K71: PIERO DELLA FRANCESCA | L71: viale federico comandino 53 | M71: URBINO | N71: URBINO | O71: www.hotelpierodellafrancesca.net | P71: info@hotelpierodellafrancesca.net
J72: ALBERGHI | K72: ALBERGO RAFFAELLO | L72: via Santa Margherita 38 | M72: URBINO | N72: URBINO | O72: www.albergoraffaello.com | P72: info@albergoraffaello.com
J73: ALBERGHI | K73: SAN DOMENICO | L73: piazza rinascimento 3 | M73: URBINO | N73: URBINO | O73: www.viphotels.it | P73: sandomenico@viphotels.it
J74: ALBERGHI | K74: SAN GIOVANNI | L74: via federico barocci 13 | M74: URBINO | N74: URBINO | O74: www.albergosangiovanniurbino.it | P74: info@albergosangiovanniurbino.it
J75: ALBERGHI | K75: TORTORINA | L75: via ottaviano petrucci 4 | M75: URBINO | N75: URBINO | O75: www.hotel-tortorina.it | P75: info@hotel-tortorina.it
... J78: ALLOGGI AGRITURISTICI | K78: AGRITURISMO FOSSO DEL LUPO | L78: via Monte Tomba 11 | M78: URBINO | N78: Scotaneto | O78: www.fossolupo.it | P78: d.garota@libero.it
J79: ALLOGGI AGRITURISTICI | K79: SANT'ANTONIO | L79: localita' gadana 55 | M79: URBINO | N79: URBINO | P79: santantonio@simail.it
J80: ALLOGGI AGRITURISTICI | K80: CALBERTARO | L80: via sant' antonio 1 | M80: URBINO | N80: URBINO | P80: calbertaro@libero.it
J81: ALLOGGI AGRITURISTICI | K81: DEI DUCHI | L81: via colonna 43 | M81: URBINO | N81: URBINO | O81: www.agriturismodeiduchi.it | P81: agriturismodeiduchi@libero.it
J82: ALLOGGI AGRITURISTICI | K82: IL PALAZZO DI MINIERA | L82: via fornace 1 | M82: URBINO | N82: URBINO | P82: renato.pulisca@gmail.com
J83: BED & BREAKFAST | K83: B&B CA' LANTE | L83: via Ca' Lante 7 | M83: URBINO | N83: URBINO | P83: tiegerie@yahoo.it
J84: ALLOGGI AGRITURISTICI | K84: VALDAPPIO | L84: via urbinate 198 | M84: URBINO | N84: URBINO | O84: www.agriturismovaldappio.it | P84: t.broccoli@libero.it
J85: ALLOGGI AGRITURISTICI | K85: PIETRA ROSA | L85: via Monte Polo 132 | M85: URBINO | N85: URBINO | O85: www.pietrarosa.it | P85: info@pietrarosa.it
J86: ALLOGGI AGRITURISTICI | K86: BELLAVISTA SAN EGIDIO | L86: via Torre Brombolona 85 | M86: URBINO | N86: URBINO
J87: ALLOGGI AGRITURISTICI | K87: CA' ANDREANA | L87: via Ca' Andreana 2 | M87: URBINO | N87: URBINO | O87: www.caandreana.it | P87: info@caandreana.it
J88: ALLOGGI AGRITURISTICI | K88: IL GRILLOTTO | L88: via del grillotto 8 | M88: URBINO | N88: URBINO | O88: www.urbinoeprovincia.com/ilgrillotto.htm | P88: mary.silvestre@alice.it
J89: ALLOGGI AGRITURISTICI | K89: VAREA/LECOSTE | L89: via dell' annunziata 35 | M89: URBINO | N89: URBINO | P89: info@varealecoste.it
J90: BED & BREAKFAST | K90: CA' LA PACINA | L90: via del Collegio 4 | M90: URBINO | N90: URBINO | O90: www.turismo.marche.it | P90: calapacina@yahoo.it
J91: BED & BREAKFAST | K91: B&B CA' IL GOVERNATORE | L91: via strada provinciale Montefabbri 30 | M91: URBINO | N91: URBINO | O91: www.ilgovernatore.it | P91: info@ilgovernatore.it
J92: TURISMO RURALE | K92: LA CELLETTA | L92: via serra di genga 7 | M92: URBINO | N92: URBINO | O92: www.lacelletta.it | P92: info@lacelletta.it
J93: ALLOGGI AGRITURISTICI | K93: MOLINO DEL TRIFOGLIO | L93: localita' repuglie 17 | M93: URBINO | N93: URBINO
J94: BED & BREAKFAST | K94: B&B CASA DOLCE CASA | L94: via San Bernardino 55 | M94: URBINO | N94: URBINO | O94: www.casadolcecasaurbino.com | P94: casadolcecasaurbino@gmail.com
J95: ALLOGGI AGRITURISTICI | K95: AGRITURISMO CA' BERTO | L95: via ca' picillo 6 | M95: URBINO | N95: URBINO | P95: ca.berto@tiscali.it
J96: TURISMO RURALE | K96: IL BIROCCIO | L96: via Ca' Bernocco 2 | M96: URBINO | N96: URBINO | O96: www.ilbiroccio.it | P96: info@ilbiroccio.it
J97: BED & BREAKFAST | K97: B&B CA' MARCHIGIANO | L97: via monte avorio 3 | M97: URBINO | N97: URBINO | O97: www.bbcamarchigiano.it | P97: info@bbcamarchigiano.it
J98: BED & BREAKFAST | K98: MONTEFELTRO | L98: via del forno 1 | M98: URBINO | N98: URBINO | O98: www.bbmontefeltro.it | P98: info@bbmontefeltro.it
J99: ALLOGGI IN AFFITTO | K99: BANCI RITA | L99: via nicolo' pellipario 49 | M99: URBINO | N99: URBINO
J100: ALLOGGI IN AFFITTO | K100: PAOLUCCI ENZO | L100: via Nicolo' Pellipario 8 | M100: URBINO | N100: URBINO
J101: ALLOGGI IN AFFITTO | K101: DAMIANI GUIDO | L101: circonvallazione Giro dei Debitori 27 | M101: URBINO | N101: URBINO
J102: ALLOGGI IN AFFITTO | K102: SCOPA ZEFFIRA | L102: via Raffaello 23 | M102: URBINO | N102: URBINO
J103: ALLOGGI IN AFFITTO | K103: PAROLO CARLA AURELIA | L103: via nicolo' pellipario 31 | M103: URBINO | N103: URBINO
...
